kstandard/__init__.pyi
kstandard/debug.py
kstandard/debug.pyi
kstandard/typing.py
kstandard/typing.pyi
kstandard-1.0.1.dist-info/METADATA
kstandard-1.0.1.dist-info/WHEEL
kstandard-1.0.1.dist-info/licenses/LICENSE
kstandard-1.0.1.dist-info/RECORD
