Metadata-Version: 2.4
Name: kstandard
Version: 1.0.1
Summary: Library with common Python code and modules I share in my projects.
Project-URL: Homepage, https://karsh.me/
Project-URL: Issues, https://github.com/karshPrime/kstandardpy
Author-email: Utkarsh Ranjan <utkarsh@cyberfear.com>
License-File: LICENSE
Classifier: License :: OSI Approved :: Apache Software License
Classifier: Operating System :: OS Independent
Classifier: Programming Language :: Python :: 3
Requires-Python: >=3.9
